{"SerializedFilePath":"G:\\OOP2\\FinalProject_GymManagementSystem\\GymManagementSystem\\obj\\Debug\\net6.0-android\\project.razor.vs.json","FilePath":"G:\\OOP2\\FinalProject_GymManagementSystem\\GymManagementSystem\\GymManagementSystem.csproj","Configuration":{"ConfigurationName":"Default","LanguageVersion":"6.0","Extensions":[]},"ProjectWorkspaceState":{"TagHelpers":[],"CSharpLanguageVersion":1000},"RootNamespace":"GymManagementSystem","Documents":[{"FilePath":"G:\\OOP2\\FinalProject_GymManagementSystem\\GymManagementSystem\\Main.razor","TargetPath":"Main.razor","FileKind":"component"},{"FilePath":"G:\\OOP2\\FinalProject_GymManagementSystem\\GymManagementSystem\\Shared\\NavMenu.razor","TargetPath":"Shared\\NavMenu.razor","FileKind":"component"},{"FilePath":"G:\\OOP2\\FinalProject_GymManagementSystem\\GymManagementSystem\\Pages\\LessonBooking.razor","TargetPath":"Pages\\LessonBooking.razor","FileKind":"component"},{"FilePath":"G:\\OOP2\\FinalProject_GymManagementSystem\\GymManagementSystem\\Shared\\SurveyPrompt.razor","TargetPath":"Shared\\SurveyPrompt.razor","FileKind":"component"},{"FilePath":"G:\\OOP2\\FinalProject_GymManagementSystem\\GymManagementSystem\\Pages\\EquipmentPage.razor","TargetPath":"Pages\\EquipmentPage.razor","FileKind":"component"},{"FilePath":"G:\\OOP2\\FinalProject_GymManagementSystem\\GymManagementSystem\\Pages\\Index.razor","TargetPath":"Pages\\Index.razor","FileKind":"component"},{"FilePath":"G:\\OOP2\\FinalProject_GymManagementSystem\\GymManagementSystem\\_Imports.razor","TargetPath":"_Imports.razor","FileKind":"componentImport"},{"FilePath":"G:\\OOP2\\FinalProject_GymManagementSystem\\GymManagementSystem\\Pages\\Location.razor","TargetPath":"Pages\\Location.razor","FileKind":"component"},{"FilePath":"G:\\OOP2\\FinalProject_GymManagementSystem\\GymManagementSystem\\Shared\\MainLayout.razor","TargetPath":"Shared\\MainLayout.razor","FileKind":"component"},{"FilePath":"G:\\OOP2\\FinalProject_GymManagementSystem\\GymManagementSystem\\Pages\\Location 1.razor","TargetPath":"Pages\\Location 1.razor","FileKind":"component"},{"FilePath":"G:\\OOP2\\FinalProject_GymManagementSystem\\GymManagementSystem\\Pages\\MemberPage.razor","TargetPath":"Pages\\MemberPage.razor","FileKind":"component"}],"SerializationFormat":"0.3"}